HandongLiDeTanhuoJiqiZhixin2018GaofenJiaochengHeji/README.md
HandongLiDeTanhuoJiqiZhixin2018GaofenJiaochengHeji/__init__.py
HandongLiDeTanhuoJiqiZhixin2018GaofenJiaochengHeji/__main__.py
HandongLiDeTanhuoJiqiZhixin2018GaofenJiaochengHeji/file.epub
HandongLiDeTanhuoJiqiZhixin2018GaofenJiaochengHeji/index.html
HandongLiDeTanhuoJiqiZhixin2018GaofenJiaochengHeji/css/__init__.py
HandongLiDeTanhuoJiqiZhixin2018GaofenJiaochengHeji/css/annotations.css
HandongLiDeTanhuoJiqiZhixin2018GaofenJiaochengHeji/css/main.css
HandongLiDeTanhuoJiqiZhixin2018GaofenJiaochengHeji/css/normalize.css
HandongLiDeTanhuoJiqiZhixin2018GaofenJiaochengHeji/css/popup.css
HandongLiDeTanhuoJiqiZhixin2018GaofenJiaochengHeji/font/__init__.py
HandongLiDeTanhuoJiqiZhixin2018GaofenJiaochengHeji/font/fontello.eot
HandongLiDeTanhuoJiqiZhixin2018GaofenJiaochengHeji/font/fontello.svg
HandongLiDeTanhuoJiqiZhixin2018GaofenJiaochengHeji/font/fontello.ttf
HandongLiDeTanhuoJiqiZhixin2018GaofenJiaochengHeji/font/fontello.woff
HandongLiDeTanhuoJiqiZhixin2018GaofenJiaochengHeji/img/__init__.py
HandongLiDeTanhuoJiqiZhixin2018GaofenJiaochengHeji/img/annotator-glyph-sprite.png
HandongLiDeTanhuoJiqiZhixin2018GaofenJiaochengHeji/img/annotator-icon-sprite.png
HandongLiDeTanhuoJiqiZhixin2018GaofenJiaochengHeji/img/apple-touch-icon.png
HandongLiDeTanhuoJiqiZhixin2018GaofenJiaochengHeji/img/cancelfullscreen.png
HandongLiDeTanhuoJiqiZhixin2018GaofenJiaochengHeji/img/close.png
HandongLiDeTanhuoJiqiZhixin2018GaofenJiaochengHeji/img/fullscreen.png
HandongLiDeTanhuoJiqiZhixin2018GaofenJiaochengHeji/img/loader.gif
HandongLiDeTanhuoJiqiZhixin2018GaofenJiaochengHeji/img/menu-icon.png
HandongLiDeTanhuoJiqiZhixin2018GaofenJiaochengHeji/img/save.png
HandongLiDeTanhuoJiqiZhixin2018GaofenJiaochengHeji/img/saved.png
HandongLiDeTanhuoJiqiZhixin2018GaofenJiaochengHeji/img/settings-s.png
HandongLiDeTanhuoJiqiZhixin2018GaofenJiaochengHeji/img/settings.png
HandongLiDeTanhuoJiqiZhixin2018GaofenJiaochengHeji/img/star.png
handong_li_de_tanhuo_jiqi_zhixin_2018_gaofen_jiaocheng_heji-2024.3.4.0.dist-info/METADATA
handong_li_de_tanhuo_jiqi_zhixin_2018_gaofen_jiaocheng_heji-2024.3.4.0.dist-info/WHEEL
handong_li_de_tanhuo_jiqi_zhixin_2018_gaofen_jiaocheng_heji-2024.3.4.0.dist-info/entry_points.txt
handong_li_de_tanhuo_jiqi_zhixin_2018_gaofen_jiaocheng_heji-2024.3.4.0.dist-info/top_level.txt
handong_li_de_tanhuo_jiqi_zhixin_2018_gaofen_jiaocheng_heji-2024.3.4.0.dist-info/RECORD
